pk4adi/__init__.py
pk4adi/pk.py
pk4adi/pk_error_cn.py
pk4adi/pkc.py
pk4adi/utils.py
pk4adi-0.1.4.dist-info/LICENSE
pk4adi-0.1.4.dist-info/METADATA
pk4adi-0.1.4.dist-info/WHEEL
pk4adi-0.1.4.dist-info/top_level.txt
pk4adi-0.1.4.dist-info/RECORD
