Metadata-Version: 2.1
Name: pk4adi
Version: 0.1.4
Summary: Using PK to Measure the Performance of Anesthetic Depth Indicators.
Home-page: https://github.com/xfz329/pk4adi.git
Author: silencejiang
Author-email: silencejiang@zju.edu.cn
License: MIT License
Platform: UNKNOWN
Classifier: License :: OSI Approved :: MIT License
Classifier: Natural Language :: English
Classifier: Operating System :: OS Independent
Classifier: Programming Language :: Python
Classifier: Programming Language :: Python :: 3.8
Classifier: Topic :: Software Development :: Libraries :: Python Modules
Requires-Python: >=3.8
License-File: LICENSE
Requires-Dist: pandas (>=0.18.0)
Requires-Dist: numpy (>=1.21.6)
Requires-Dist: scipy (>=1.9.0)
Requires-Dist: tabulate
